Metadata-Version: 1.0
Name: distributions-learn
Version: 0.1
Summary: Gaussian and Binomial distributions
Home-page: UNKNOWN
Author: Nikhil Jose
Author-email: UNKNOWN
License: UNKNOWN
Platform: UNKNOWN
